LICENSE.txt
MANIFEST.in
README.rst
requirements.txt
setup.py
lyrics/.__init__.py.swp
lyrics/.database.py.swp
lyrics/.fetcher.py.swp
lyrics/.id3.py.swp
lyrics/.settings.py.swp
lyrics/__init__.py
lyrics/__init__.pyc
lyrics/_compatibility.py
lyrics/_compatibility.pyc
lyrics/database.py
lyrics/database.pyc
lyrics/debug.py
lyrics/debug.pyc
lyrics/fetcher.py
lyrics/fetcher.pyc
lyrics/id3.py
lyrics/id3.pyc
lyrics/settings.py
lyrics/settings.pyc
lyrics.egg-info/PKG-INFO
lyrics.egg-info/SOURCES.txt
lyrics.egg-info/dependency_links.txt
lyrics.egg-info/entry_points.txt
lyrics.egg-info/requires.txt
lyrics.egg-info/top_level.txt
lyrics/apps/__init__.py
lyrics/apps/__init__.pyc
lyrics/apps/console/.__init__.py.swp
lyrics/apps/console/.app.py.swp
lyrics/apps/console/.color.py.swp
lyrics/apps/console/.keys.py.swp
lyrics/apps/console/.log.py.swp
lyrics/apps/console/.player.py.swp
lyrics/apps/console/.playlist.py.swp
lyrics/apps/console/.radio.py.swp
lyrics/apps/console/.states.py.swp
lyrics/apps/console/__init__.py
lyrics/apps/console/__init__.pyc
lyrics/apps/console/app.py
lyrics/apps/console/app.pyc
lyrics/apps/console/color.py
lyrics/apps/console/color.pyc
lyrics/apps/console/database.pyc
lyrics/apps/console/keys.py
lyrics/apps/console/keys.pyc
lyrics/apps/console/log.py
lyrics/apps/console/player.py
lyrics/apps/console/player.pyc
lyrics/apps/console/playlist.py
lyrics/apps/console/playlist.pyc
lyrics/apps/console/radio.py
lyrics/apps/console/states.py
lyrics/apps/console/states.pyc
lyrics/apps/console/pyradio/.DESCRIPTION.swp
lyrics/apps/console/pyradio/.gitignore
lyrics/apps/console/pyradio/Changelog
lyrics/apps/console/pyradio/DESCRIPTION
lyrics/apps/console/pyradio/LICENCE
lyrics/apps/console/pyradio/MANIFEST.in
lyrics/apps/console/pyradio/Makefile
lyrics/apps/console/pyradio/README.md
lyrics/apps/console/pyradio/setup.py
lyrics/apps/console/pyradio/.git/HEAD
lyrics/apps/console/pyradio/.git/config
lyrics/apps/console/pyradio/.git/description
lyrics/apps/console/pyradio/.git/index
lyrics/apps/console/pyradio/.git/packed-refs
lyrics/apps/console/pyradio/.git/hooks/applypatch-msg.sample
lyrics/apps/console/pyradio/.git/hooks/commit-msg.sample
