Metadata-Version: 1.0
Name: lyrics
Version: 0.0.3
Summary: Play music and view the lyrics.
Home-page:  http://github.com/davidhalter/lyrics
Author: David Halter
Author-email: UNKNOWN
License: GPL 3
Platform: Any
